sys2txt/__init__.py
sys2txt/__main__.py
sys2txt/audio.py
sys2txt/constants.py
sys2txt/pulse.py
sys2txt/transcribe.py
sys2txt/utils.py
sys2txt-0.1.1.post1.dist-info/licenses/LICENSE
sys2txt-0.1.1.post1.dist-info/METADATA
sys2txt-0.1.1.post1.dist-info/WHEEL
sys2txt-0.1.1.post1.dist-info/entry_points.txt
sys2txt-0.1.1.post1.dist-info/top_level.txt
sys2txt-0.1.1.post1.dist-info/RECORD
