Metadata-Version: 2.4
Name: sys2txt
Version: 0.1.1.post1
Summary: Record system audio and transcribe to text using AI
Author-email: Joe Heffer <jheffer@gmail.com>
License: MIT
Requires-Python: >=3.9
License-File: LICENSE
Requires-Dist: faster-whisper>=1.0.0
Requires-Dist: openai-whisper>=20231117
Provides-Extra: dev
Requires-Dist: ruff>=0.8.0; extra == "dev"
Dynamic: license-file
